CHANGES.md
LICENSE
MANIFEST.in
README.md
setup.cfg
setup.py
btx/__init__.py
btx.egg-info/PKG-INFO
btx.egg-info/SOURCES.txt
btx.egg-info/dependency_links.txt
btx.egg-info/entry_points.txt
btx.egg-info/not-zip-safe
btx.egg-info/requires.txt
btx.egg-info/top_level.txt