Metadata-Version: 1.1
Name: btx
Version: 0.1
Summary: A botocore helper class
Home-page: https://github.com/reedobrien/btx
Author: Reed O'Brien
Author-email: reed.foss@reedobrien.com
License: BSD-derived. See LICENSE file
Keywords: AWS botocore
Platform: UNKNOWN
Classifier: Intended Audience :: Developers
Classifier: Programming Language :: Python
